app_paths/__init__.py
app_paths/base.py
app_paths/io.py
app_paths/paths.py
app_paths/types.py
app_paths-0.0.8.dist-info/LICENSE
app_paths-0.0.8.dist-info/METADATA
app_paths-0.0.8.dist-info/WHEEL
app_paths-0.0.8.dist-info/top_level.txt
app_paths-0.0.8.dist-info/zip-safe
app_paths-0.0.8.dist-info/RECORD
